onnxscript/__init__.py
onnxscript/converter.py
onnxscript/converter_test.py
onnxscript/evaluator.py
onnxscript/evaluator_test.py
onnxscript/irbuilder.py
onnxscript/main.py
onnxscript/onnx_types.py
onnxscript/py.typed
onnxscript/sourceinfo.py
onnxscript/tensor.py
onnxscript/tensor_test.py
onnxscript/testing.py
onnxscript/type_annotation.py
onnxscript/type_annotation_test.py
onnxscript/values.py
onnxscript/values_test.py
onnxscript/_internal/__init__.py
onnxscript/_internal/analysis.py
onnxscript/_internal/analysis_test.py
onnxscript/_internal/ast_utils.py
onnxscript/_internal/autocast.py
onnxscript/_internal/param_manipulation.py
onnxscript/_internal/param_manipulation_test.py
onnxscript/_internal/runtime_typing.py
onnxscript/_internal/utils.py
onnxscript/_internal/version_utils.py
onnxscript/backend/__init__.py
onnxscript/backend/onnx_backend.py
onnxscript/backend/onnx_backend_test.py
onnxscript/backend/onnx_export.py
onnxscript/backend/onnx_export_test.py
onnxscript/diagnostics/infra/__init__.py
onnxscript/diagnostics/infra/_infra.py
onnxscript/diagnostics/infra/context.py
onnxscript/diagnostics/infra/decorator.py
onnxscript/diagnostics/infra/formatter.py
onnxscript/diagnostics/infra/utils.py
onnxscript/diagnostics/infra/sarif/__init__.py
onnxscript/diagnostics/infra/sarif/_address.py
onnxscript/diagnostics/infra/sarif/_artifact.py
onnxscript/diagnostics/infra/sarif/_artifact_change.py
onnxscript/diagnostics/infra/sarif/_artifact_content.py
onnxscript/diagnostics/infra/sarif/_artifact_location.py
onnxscript/diagnostics/infra/sarif/_attachment.py
onnxscript/diagnostics/infra/sarif/_code_flow.py
onnxscript/diagnostics/infra/sarif/_configuration_override.py
onnxscript/diagnostics/infra/sarif/_conversion.py
onnxscript/diagnostics/infra/sarif/_edge.py
onnxscript/diagnostics/infra/sarif/_edge_traversal.py
onnxscript/diagnostics/infra/sarif/_exception.py
onnxscript/diagnostics/infra/sarif/_external_properties.py
onnxscript_preview-0.1.0.dev20230907.dist-info/LICENSE
onnxscript_preview-0.1.0.dev20230907.dist-info/METADATA
onnxscript_preview-0.1.0.dev20230907.dist-info/WHEEL
onnxscript_preview-0.1.0.dev20230907.dist-info/top_level.txt
onnxscript_preview-0.1.0.dev20230907.dist-info/RECORD
