Metadata-Version: 2.1
Name: onnxscript-preview
Version: 0.1.0.dev20230907
Summary: Naturally author ONNX functions and models using a subset of Python
Author-email: Microsoft Corporation <onnx@microsoft.com>
License: MIT License
Project-URL: Repository, https://github.com/microsoft/onnxscript
Classifier: Development Status :: 4 - Beta
Classifier: Environment :: Console
Classifier: Intended Audience :: Developers
Classifier: Operating System :: POSIX
Classifier: Operating System :: MacOS :: MacOS X
Classifier: Operating System :: Microsoft :: Windows
Classifier: Programming Language :: Python :: 3.8
Classifier: Programming Language :: Python :: 3.9
Classifier: Programming Language :: Python :: 3.10
Classifier: Programming Language :: Python :: 3.11
Classifier: License :: OSI Approved :: MIT License
Requires-Python: >=3.8
License-File: LICENSE
Requires-Dist: numpy
Requires-Dist: onnx >=1.14
Requires-Dist: typing-extensions
